{
    "id": 79244693,
    "name": "Quantum Dynamix",
    "author": "GrenadeofTacos",
    "creators": [
        "Riot",
        "icedcave",
        "G-Force",
        "silver",
        "xSmokes",
        "nikroplays",
        "Luckyy",
        "GrenadeofTacos",
        "CuLuC",
        "Genoxide",
        "RobTop",
        "Aurorus",
        "Awedsy",
        "Komp"
    ],
    "verifier": "Cersia",
    "verification": "https://youtu.be/SjQV6uJOtyQ",
    "percentToQualify": 69,
    "password": "111111",
    "records": []
}
